tubeConverter/__init__.py
tubeConverter/module.py
tubeConverter-0.0.1.dist-info/LICENSE
tubeConverter-0.0.1.dist-info/METADATA
tubeConverter-0.0.1.dist-info/WHEEL
tubeConverter-0.0.1.dist-info/top_level.txt
tubeConverter-0.0.1.dist-info/RECORD
