Metadata-Version: 2.1
Name: tubeConverter
Version: 0.0.1
Summary: Package based on pytube to download videos, audios, playlists of videos and playlists of audios as well
Author: Oumayma EL-FAHSI
Author-email: <oumayma.elfahsi@ump.ac.ma>
Keywords: Python,Videos,Music,Playlist music,Playlist videos,OOP,YouTube,Converter
Classifier: Intended Audience :: Developers
Classifier: Programming Language :: Python :: 3
License-File: LICENSE
Requires-Dist: pytube
